Metadata-Version: 1.1
Name: rqr
Version: 0.2.0
Summary: Python ReQuiRements
Home-page: https://github.com/noxan/rqr
Author: Richard
Author-email: hello@noxan.net
License: MIT
Keywords: development requirements manager
Platform: UNKNOWN
Classifier: Development Status :: 3 - Alpha
Classifier: Intended Audience :: Developers
Classifier: License :: OSI Approved :: MIT License
Classifier: Programming Language :: Python :: 3
Classifier: Programming Language :: Python :: 3.5
